README
setup.py
pypgwrap/__init__.py
pypgwrap/cli.py
pypgwrap/connection.py
pypgwrap/context.py
pypgwrap/cursor.py
pypgwrap/pool.py
pypgwrap/sqlop.py
pypgwrap.egg-info/PKG-INFO
pypgwrap.egg-info/SOURCES.txt
pypgwrap.egg-info/dependency_links.txt
pypgwrap.egg-info/top_level.txt