Metadata-Version: 1.1
Name: pypgwrap
Version: 0.1.15
Summary: PostgreSQL database wrapper - provides wrapper over psycopg2 supporting a Python API for common sql functions, transaction and pooling
Home-page: https://github.com/ephillipe/pypgwrap
Author: Erick Almeida
Author-email: ephillipe@gmail.com
License: BSD
Platform: any
Classifier: Topic :: Database
Requires: psycopg2
